{"text": "Catatan : Bukti transpor perjalanan ke Bukittinggi naik bus Rp. 25.000,- dan Bus | tidak ada menyediakan Tiket. Dari pemberhentian bus ke Istana Bung Hatta naik ojek konvensional yang tdk ada bukti pembayarannya sebesar Rp.10.000,-. Foto naik bus a Fr ae an Wea) . Ae Apt 30 2P26 easier xs, BM dene a Fousatdileje Padangeatno “eam PON BA een aig oe pe Sek a Pra, i B cabup Sin ac e Oe n Sebi", "confidence": 58.41, "words": [{"text": "Catatan", "confidence": 91.0, "left": 270, "top": 235, "width": 117, "height": 27, "page": 0, "rotation": 0}, {"text": ":", "confidence": 92.0, "left": 402, "top": 244, "width": 4, "height": 19, "page": 0, "rotation": 0}, {"text": "Bukti", "confidence": 91.0, "left": 421, "top": 238, "width": 71, "height": 26, "page": 0, "rotation": 0}, {"text": "transpor", "confidence": 89.0, "left": 505, "top": 239, "width": 126, "height": 32, "page": 0, "rotation": 0}, {"text": "perjalanan", "confidence": 92.0, "left": 642, "top": 240, "width": 156, "height": 32, "page": 0, "rotation": 0}, {"text": "ke", "confidence": 93.0, "left": 812, "top": 241, "width": 33, "height": 26, "page": 0, "rotation": 0}, {"text": "Bukittinggi", "confidence": 91.0, "left": 859, "top": 242, "width": 152, "height": 33, "page": 0, "rotation": 0}, {"text": "naik", "confidence": 91.0, "left": 1025, "top": 244, "width": 60, "height": 26, "page": 0, "rotation": 0}, {"text": "bus", "confidence": 91.0, "left": 1098, "top": 244, "width": 52, "height": 26, "page": 0, "rotation": 0}, {"text": "Rp.", "confidence": 92.0, "left": 1165, "top": 245, "width": 47, "height": 33, "page": 0, "rotation": 0}, {"text": "25.000,-", "confidence": 91.0, "left": 1225, "top": 246, "width": 125, "height": 31, "page": 0, "rotation": 0}, {"text": "dan", "confidence": 91.0, "left": 1362, "top": 247, "width": 53, "height": 26, "page": 0, "rotation": 0}, {"text": "Bus", "confidence": 90.0, "left": 1430, "top": 248, "width": 56, "height": 26, "page": 0, "rotation": 0}, {"text": "|", "confidence": 46.0, "left": 0, "top": 294, "width": 1, "height": 3, "page": 0, "rotation": 0}, {"text": "tidak", "confidence": 96.0, "left": 269, "top": 278, "width": 71, "height": 26, "page": 0, "rotation": 0}, {"text": "ada", "confidence": 93.0, "left": 352, "top": 279, "width": 54, "height": 26, "page": 0, "rotation": 0}, {"text": "menyediakan", "confidence": 91.0, "left": 420, "top": 281, "width": 201, "height": 32, "page": 0, "rotation": 0}, {"text": "Tiket.", "confidence": 91.0, "left": 632, "top": 282, "width": 82, "height": 26, "page": 0, "rotation": 0}, {"text": "Dari", "confidence": 91.0, "left": 729, "top": 283, "width": 58, "height": 26, "page": 0, "rotation": 0}, {"text": "pemberhentian", "confidence": 91.0, "left": 801, "top": 284, "width": 225, "height": 32, "page": 0, "rotation": 0}, {"text": "bus", "confidence": 96.0, "left": 1039, "top": 286, "width": 53, "height": 26, "page": 0, "rotation": 0}, {"text": "ke", "confidence": 96.0, "left": 1104, "top": 287, "width": 33, "height": 25, "page": 0, "rotation": 0}, {"text": "Istana", "confidence": 96.0, "left": 1151, "top": 287, "width": 89, "height": 27, "page": 0, "rotation": 0}, {"text": "Bung", "confidence": 96.0, "left": 1254, "top": 288, "width": 76, "height": 33, "page": 0, "rotation": 0}, {"text": "Hatta", "confidence": 93.0, "left": 1344, "top": 289, "width": 77, "height": 27, "page": 0, "rotation": 0}, {"text": "naik", "confidence": 90.0, "left": 1435, "top": 291, "width": 61, "height": 26, "page": 0, "rotation": 0}, {"text": "ojek", "confidence": 92.0, "left": 269, "top": 322, "width": 61, "height": 32, "page": 0, "rotation": 0}, {"text": "konvensional", "confidence": 91.0, "left": 343, "top": 322, "width": 197, "height": 28, "page": 0, "rotation": 0}, {"text": "yang", "confidence": 93.0, "left": 553, "top": 331, "width": 71, "height": 26, "page": 0, "rotation": 0}, {"text": "tdk", "confidence": 93.0, "left": 637, "top": 326, "width": 45, "height": 25, "page": 0, "rotation": 0}, {"text": "ada", "confidence": 93.0, "left": 692, "top": 326, "width": 55, "height": 26, "page": 0, "rotation": 0}, {"text": "bukti", "confidence": 91.0, "left": 760, "top": 327, "width": 69, "height": 26, "page": 0, "rotation": 0}, {"text": "pembayarannya", "confidence": 91.0, "left": 843, "top": 328, "width": 241, "height": 34, "page": 0, "rotation": 0}, {"text": "sebesar", "confidence": 92.0, "left": 1097, "top": 330, "width": 122, "height": 27, "page": 0, "rotation": 0}, {"text": "Rp.10.000,-.", "confidence": 85.0, "left": 1230, "top": 328, "width": 184, "height": 42, "page": 0, "rotation": 0}, {"text": "Foto", "confidence": 87.0, "left": 269, "top": 407, "width": 66, "height": 26, "page": 0, "rotation": 0}, {"text": "naik", "confidence": 87.0, "left": 358, "top": 408, "width": 60, "height": 26, "page": 0, "rotation": 0}, {"text": "bus", "confidence": 95.0, "left": 430, "top": 409, "width": 53, "height": 26, "page": 0, "rotation": 0}, {"text": "a", "confidence": 1.0, "left": 460, "top": 1064, "width": 47, "height": 25, "page": 0, "rotation": 0}, {"text": "Fr", "confidence": 20.0, "left": 551, "top": 1065, "width": 91, "height": 27, "page": 0, "rotation": 0}, {"text": "ae", "confidence": 42.0, "left": 681, "top": 1065, "width": 78, "height": 29, "page": 0, "rotation": 0}, {"text": "an", "confidence": 31.0, "left": 779, "top": 1071, "width": 66, "height": 26, "page": 0, "rotation": 0}, {"text": "Wea)", "confidence": 2.0, "left": 854, "top": 1079, "width": 108, "height": 22, "page": 0, "rotation": 0}, {"text": ".", "confidence": 20.0, "left": 1034, "top": 1070, "width": 39, "height": 24, "page": 0, "rotation": 0}, {"text": "Ae", "confidence": 8.0, "left": 1132, "top": 1073, "width": 92, "height": 24, "page": 0, "rotation": 0}, {"text": "Apt", "confidence": 73.0, "left": 1285, "top": 1072, "width": 68, "height": 28, "page": 0, "rotation": 0}, {"text": "30", "confidence": 71.0, "left": 1330, "top": 1061, "width": 26, "height": 44, "page": 0, "rotation": 0}, {"text": "2P26", "confidence": 47.0, "left": 1366, "top": 1072, "width": 47, "height": 27, "page": 0, "rotation": 0}, {"text": "easier", "confidence": 6.0, "left": 1424, "top": 1073, "width": 112, "height": 28, "page": 0, "rotation": 0}, {"text": "xs,", "confidence": 44.0, "left": 484, "top": 1089, "width": 115, "height": 30, "page": 0, "rotation": 0}, {"text": "BM", "confidence": 10.0, "left": 681, "top": 1091, "width": 113, "height": 36, "page": 0, "rotation": 0}, {"text": "dene", "confidence": 24.0, "left": 832, "top": 1107, "width": 16, "height": 15, "page": 0, "rotation": 0}, {"text": "a", "confidence": 13.0, "left": 987, "top": 1096, "width": 58, "height": 34, "page": 0, "rotation": 0}, {"text": "Fousatdileje", "confidence": 0.0, "left": 1075, "top": 1079, "width": 163, "height": 63, "page": 0, "rotation": 0}, {"text": "Padangeatno", "confidence": 0.0, "left": 1249, "top": 1099, "width": 158, "height": 33, "page": 0, "rotation": 0}, {"text": "“eam", "confidence": 0.0, "left": 1422, "top": 1099, "width": 120, "height": 33, "page": 0, "rotation": 0}, {"text": "PON", "confidence": 36.0, "left": 527, "top": 1148, "width": 82, "height": 31, "page": 0, "rotation": 0}, {"text": "BA", "confidence": 40.0, "left": 699, "top": 1152, "width": 11, "height": 26, "page": 0, "rotation": 0}, {"text": "een", "confidence": 26.0, "left": 721, "top": 1152, "width": 175, "height": 28, "page": 0, "rotation": 0}, {"text": "aig", "confidence": 34.0, "left": 909, "top": 1151, "width": 52, "height": 57, "page": 0, "rotation": 0}, {"text": "oe", "confidence": 28.0, "left": 1039, "top": 1159, "width": 91, "height": 23, "page": 0, "rotation": 0}, {"text": "pe", "confidence": 23.0, "left": 1159, "top": 1161, "width": 22, "height": 22, "page": 0, "rotation": 0}, {"text": "Sek", "confidence": 5.0, "left": 1252, "top": 1158, "width": 148, "height": 27, "page": 0, "rotation": 0}, {"text": "a", "confidence": 10.0, "left": 1413, "top": 1160, "width": 128, "height": 24, "page": 0, "rotation": 0}, {"text": "Pra,", "confidence": 21.0, "left": 477, "top": 1177, "width": 77, "height": 24, "page": 0, "rotation": 0}, {"text": "i", "confidence": 70.0, "left": 615, "top": 1192, "width": 3, "height": 4, "page": 0, "rotation": 0}, {"text": "B", "confidence": 28.0, "left": 690, "top": 1175, "width": 121, "height": 30, "page": 0, "rotation": 0}, {"text": "cabup", "confidence": 10.0, "left": 824, "top": 1185, "width": 10, "height": 18, "page": 0, "rotation": 0}, {"text": "Sin", "confidence": 23.0, "left": 857, "top": 1182, "width": 37, "height": 22, "page": 0, "rotation": 0}, {"text": "ac", "confidence": 68.0, "left": 906, "top": 1184, "width": 20, "height": 24, "page": 0, "rotation": 0}, {"text": "e", "confidence": 30.0, "left": 1040, "top": 1181, "width": 121, "height": 26, "page": 0, "rotation": 0}, {"text": "Oe", "confidence": 17.0, "left": 1242, "top": 1181, "width": 92, "height": 23, "page": 0, "rotation": 0}, {"text": "n", "confidence": 0.0, "left": 1393, "top": 1186, "width": 31, "height": 22, "page": 0, "rotation": 0}, {"text": "Sebi", "confidence": 0.0, "left": 1430, "top": 1186, "width": 113, "height": 27, "page": 0, "rotation": 0}], "engine": "tesseract", "warnings": [], "rotation": 0, "tried_rotations": [0, 90, 180, 270], "cache_hit": false}