{"text": "BADAN PUSAT STATISTIK BADAN PUSAT STATISTIK PROP. SUMATERA BARAT SURAT PERINTAH MEMBAYAR Nomor 00100A Tanggal 28-Apr-2026 Halaman 2 dari 2 Kuasa Bendahara Umum KPPN Padang (010) Agar melakukan pembayaran tagihan sejumlah Rp 51.040.959,00 “LIMA PULUH SATU JUTA EMPAT PULUH RIBU SEMBILAN RATUS LIMA PULUH SEMBILAN RUPIAH **** Tahun Anggaran 2026 Jenis Tagihan : GUP Dasar Pembayaran Jatuh Tempo : Segera DIPA No. : DIPA-054.01.2.019937/2026 Cara Bayar : SP2D Tanggal : 01-Dec-2025 UU 17/2025 TENTANG APBN TAHUN ANGGARAN 2026 TOTAL PEMBAYARAN 51.040.959,00 a Kepada: Nomor : 847748 Bank / Pos : BANK NEGARA INDONESIA Nama Supplier ; BADAN PUSAT STATISTIK PROP. SUMATERA Rekening : 989075019937 1000 BARAT a . NPWP2 : 0001858539201000 ama sae . NOP : Uraian : PENGGANTIAN UANG PERSEDIAAN UNTUK KEPERLUAN BELANJA BARANG DENGAN NOMOR SERTIFIKAT BNT : BNT- 01424/191/691/2023 TANGGAL 3 APRIL 2023 Semua bukti-bukti pengeluaran yang disahkan Pejabat Pembuat Komitmen telah Padang, 28 April 2026 diuji dan dinyatakan memenuhi persyaratan untuk dilakukan pembayaran atas a.n Kuasa Pengguna Anggaran beban APBN, selanjutnya bukti-bukti pengeluaran dimaksud disimpan dan Pejabat Penandatangan SPM ditatausahakan oleh Pejabat Penandatangan SPM ! 9 Kebenaran perhitungan dan isi yang tertuang dalam SPM ini menjadi tanggung Hk jawab Pejabat Penandatangan SPM. ES - Oke: ie Dokumen ini telah ditandatangani menggunakan sertifikat elektronik yang ca Sa diterbitkan oleh Balai Besar Sertifikat Elektronik (BSrE), BSSN. JEFRIO MARTIYUS poe Teh NIP 198807 162010121007", "confidence": 85.09, "words": [{"text": "BADAN", "confidence": 92.0, "left": 749, "top": 119, "width": 92, "height": 20, "page": 0, "rotation": 0}, {"text": "PUSAT", "confidence": 92.0, "left": 851, "top": 119, "width": 88, "height": 20, "page": 0, "rotation": 0}, {"text": "STATISTIK", "confidence": 91.0, "left": 947, "top": 118, "width": 134, "height": 21, "page": 0, "rotation": 0}, {"text": "BADAN", "confidence": 90.0, "left": 576, "top": 154, "width": 92, "height": 20, "page": 0, "rotation": 0}, {"text": "PUSAT", "confidence": 90.0, "left": 678, "top": 154, "width": 88, "height": 20, "page": 0, "rotation": 0}, {"text": "STATISTIK", "confidence": 90.0, "left": 775, "top": 154, "width": 134, "height": 20, "page": 0, "rotation": 0}, {"text": "PROP.", "confidence": 91.0, "left": 918, "top": 154, "width": 80, "height": 20, "page": 0, "rotation": 0}, {"text": "SUMATERA", "confidence": 92.0, "left": 1006, "top": 154, "width": 149, "height": 20, "page": 0, "rotation": 0}, {"text": "BARAT", "confidence": 92.0, "left": 1164, "top": 154, "width": 90, "height": 20, "page": 0, "rotation": 0}, {"text": "SURAT", "confidence": 91.0, "left": 718, "top": 189, "width": 90, "height": 21, "page": 0, "rotation": 0}, {"text": "PERINTAH", "confidence": 91.0, "left": 816, "top": 189, "width": 132, "height": 21, "page": 0, "rotation": 0}, {"text": "MEMBAYAR", "confidence": 90.0, "left": 958, "top": 189, "width": 153, "height": 21, "page": 0, "rotation": 0}, {"text": "Nomor", "confidence": 87.0, "left": 140, "top": 229, "width": 78, "height": 20, "page": 0, "rotation": 0}, {"text": "00100A", "confidence": 89.0, "left": 236, "top": 229, "width": 90, "height": 20, "page": 0, "rotation": 0}, {"text": "Tanggal", "confidence": 90.0, "left": 794, "top": 228, "width": 94, "height": 26, "page": 0, "rotation": 0}, {"text": "28-Apr-2026", "confidence": 95.0, "left": 917, "top": 228, "width": 146, "height": 26, "page": 0, "rotation": 0}, {"text": "Halaman", "confidence": 89.0, "left": 1347, "top": 229, "width": 102, "height": 20, "page": 0, "rotation": 0}, {"text": "2", "confidence": 92.0, "left": 1481, "top": 229, "width": 13, "height": 20, "page": 0, "rotation": 0}, {"text": "dari", "confidence": 79.0, "left": 1574, "top": 229, "width": 42, "height": 21, "page": 0, "rotation": 0}, {"text": "2", "confidence": 79.0, "left": 1651, "top": 229, "width": 13, "height": 20, "page": 0, "rotation": 0}, {"text": "Kuasa", "confidence": 92.0, "left": 125, "top": 292, "width": 72, "height": 21, "page": 0, "rotation": 0}, {"text": "Bendahara", "confidence": 96.0, "left": 207, "top": 292, "width": 126, "height": 21, "page": 0, "rotation": 0}, {"text": "Umum", "confidence": 96.0, "left": 344, "top": 293, "width": 75, "height": 20, "page": 0, "rotation": 0}, {"text": "KPPN", "confidence": 91.0, "left": 520, "top": 292, "width": 69, "height": 21, "page": 0, "rotation": 0}, {"text": "Padang", "confidence": 96.0, "left": 600, "top": 292, "width": 88, "height": 25, "page": 0, "rotation": 0}, {"text": "(010)", "confidence": 96.0, "left": 698, "top": 292, "width": 59, "height": 25, "page": 0, "rotation": 0}, {"text": "Agar", "confidence": 93.0, "left": 123, "top": 336, "width": 57, "height": 25, "page": 0, "rotation": 0}, {"text": "melakukan", "confidence": 73.0, "left": 187, "top": 336, "width": 125, "height": 20, "page": 0, "rotation": 0}, {"text": "pembayaran", "confidence": 91.0, "left": 322, "top": 336, "width": 144, "height": 25, "page": 0, "rotation": 0}, {"text": "tagihan", "confidence": 92.0, "left": 475, "top": 336, "width": 85, "height": 25, "page": 0, "rotation": 0}, {"text": "sejumlah", "confidence": 90.0, "left": 569, "top": 336, "width": 104, "height": 25, "page": 0, "rotation": 0}, {"text": "Rp", "confidence": 93.0, "left": 781, "top": 336, "width": 31, "height": 25, "page": 0, "rotation": 0}, {"text": "51.040.959,00", "confidence": 92.0, "left": 823, "top": 336, "width": 167, "height": 23, "page": 0, "rotation": 0}, {"text": "“LIMA", "confidence": 33.0, "left": 251, "top": 394, "width": 116, "height": 20, "page": 0, "rotation": 0}, {"text": "PULUH", "confidence": 90.0, "left": 376, "top": 394, "width": 86, "height": 21, "page": 0, "rotation": 0}, {"text": "SATU", "confidence": 90.0, "left": 472, "top": 394, "width": 68, "height": 21, "page": 0, "rotation": 0}, {"text": "JUTA", "confidence": 90.0, "left": 549, "top": 394, "width": 66, "height": 21, "page": 0, "rotation": 0}, {"text": "EMPAT", "confidence": 90.0, "left": 624, "top": 394, "width": 89, "height": 20, "page": 0, "rotation": 0}, {"text": "PULUH", "confidence": 88.0, "left": 722, "top": 394, "width": 86, "height": 21, "page": 0, "rotation": 0}, {"text": "RIBU", "confidence": 92.0, "left": 818, "top": 394, "width": 60, "height": 21, "page": 0, "rotation": 0}, {"text": "SEMBILAN", "confidence": 91.0, "left": 888, "top": 394, "width": 131, "height": 21, "page": 0, "rotation": 0}, {"text": "RATUS", "confidence": 92.0, "left": 1029, "top": 394, "width": 87, "height": 21, "page": 0, "rotation": 0}, {"text": "LIMA", "confidence": 92.0, "left": 1126, "top": 394, "width": 60, "height": 21, "page": 0, "rotation": 0}, {"text": "PULUH", "confidence": 91.0, "left": 1195, "top": 394, "width": 86, "height": 21, "page": 0, "rotation": 0}, {"text": "SEMBILAN", "confidence": 91.0, "left": 1291, "top": 395, "width": 131, "height": 20, "page": 0, "rotation": 0}, {"text": "RUPIAH", "confidence": 92.0, "left": 1432, "top": 395, "width": 97, "height": 20, "page": 0, "rotation": 0}, {"text": "****", "confidence": 90.0, "left": 1539, "top": 395, "width": 38, "height": 9, "page": 0, "rotation": 0}, {"text": "Tahun", "confidence": 90.0, "left": 123, "top": 481, "width": 74, "height": 20, "page": 0, "rotation": 0}, {"text": "Anggaran", "confidence": 90.0, "left": 205, "top": 481, "width": 113, "height": 25, "page": 0, "rotation": 0}, {"text": "2026", "confidence": 96.0, "left": 352, "top": 481, "width": 58, "height": 20, "page": 0, "rotation": 0}, {"text": "Jenis", "confidence": 90.0, "left": 1178, "top": 481, "width": 61, "height": 20, "page": 0, "rotation": 0}, {"text": "Tagihan", "confidence": 76.0, "left": 1246, "top": 481, "width": 95, "height": 25, "page": 0, "rotation": 0}, {"text": ":", "confidence": 26.0, "left": 1379, "top": 487, "width": 4, "height": 14, "page": 0, "rotation": 0}, {"text": "GUP", "confidence": 89.0, "left": 1404, "top": 481, "width": 56, "height": 20, "page": 0, "rotation": 0}, {"text": "Dasar", "confidence": 92.0, "left": 124, "top": 510, "width": 70, "height": 21, "page": 0, "rotation": 0}, {"text": "Pembayaran", "confidence": 92.0, "left": 202, "top": 510, "width": 147, "height": 26, "page": 0, "rotation": 0}, {"text": "Jatuh", "confidence": 91.0, "left": 1178, "top": 516, "width": 63, "height": 21, "page": 0, "rotation": 0}, {"text": "Tempo", "confidence": 62.0, "left": 1250, "top": 516, "width": 81, "height": 26, "page": 0, "rotation": 0}, {"text": ":", "confidence": 62.0, "left": 1379, "top": 522, "width": 4, "height": 15, "page": 0, "rotation": 0}, {"text": "Segera", "confidence": 90.0, "left": 1404, "top": 516, "width": 83, "height": 26, "page": 0, "rotation": 0}, {"text": "DIPA", "confidence": 92.0, "left": 125, "top": 546, "width": 60, "height": 20, "page": 0, "rotation": 0}, {"text": "No.", "confidence": 93.0, "left": 194, "top": 546, "width": 38, "height": 20, "page": 0, "rotation": 0}, {"text": ":", "confidence": 86.0, "left": 242, "top": 551, "width": 4, "height": 15, "page": 0, "rotation": 0}, {"text": "DIPA-054.01.2.019937/2026", "confidence": 90.0, "left": 256, "top": 545, "width": 314, "height": 20, "page": 0, "rotation": 0}, {"text": "Cara", "confidence": 96.0, "left": 1179, "top": 552, "width": 54, "height": 21, "page": 0, "rotation": 0}, {"text": "Bayar", "confidence": 96.0, "left": 1243, "top": 552, "width": 69, "height": 26, "page": 0, "rotation": 0}, {"text": ":", "confidence": 88.0, "left": 1379, "top": 558, "width": 4, "height": 15, "page": 0, "rotation": 0}, {"text": "SP2D", "confidence": 75.0, "left": 1404, "top": 552, "width": 67, "height": 21, "page": 0, "rotation": 0}, {"text": "Tanggal", "confidence": 91.0, "left": 123, "top": 581, "width": 95, "height": 27, "page": 0, "rotation": 0}, {"text": ":", "confidence": 88.0, "left": 242, "top": 587, "width": 4, "height": 15, "page": 0, "rotation": 0}, {"text": "01-Dec-2025", "confidence": 96.0, "left": 256, "top": 582, "width": 151, "height": 20, "page": 0, "rotation": 0}, {"text": "UU", "confidence": 96.0, "left": 125, "top": 614, "width": 35, "height": 20, "page": 0, "rotation": 0}, {"text": "17/2025", "confidence": 92.0, "left": 171, "top": 614, "width": 92, "height": 21, "page": 0, "rotation": 0}, {"text": "TENTANG", "confidence": 90.0, "left": 271, "top": 614, "width": 125, "height": 20, "page": 0, "rotation": 0}, {"text": "APBN", "confidence": 90.0, "left": 404, "top": 614, "width": 70, "height": 20, "page": 0, "rotation": 0}, {"text": "TAHUN", "confidence": 89.0, "left": 484, "top": 614, "width": 89, "height": 21, "page": 0, "rotation": 0}, {"text": "ANGGARAN", "confidence": 92.0, "left": 123, "top": 645, "width": 149, "height": 20, "page": 0, "rotation": 0}, {"text": "2026", "confidence": 96.0, "left": 282, "top": 645, "width": 57, "height": 20, "page": 0, "rotation": 0}, {"text": "TOTAL", "confidence": 93.0, "left": 496, "top": 805, "width": 87, "height": 20, "page": 0, "rotation": 0}, {"text": "PEMBAYARAN", "confidence": 91.0, "left": 592, "top": 805, "width": 186, "height": 20, "page": 0, "rotation": 0}, {"text": "51.040.959,00", "confidence": 84.0, "left": 1546, "top": 806, "width": 167, "height": 23, "page": 0, "rotation": 0}, {"text": "a", "confidence": 0.0, "left": 103, "top": 836, "width": 1051, "height": 785, "page": 0, "rotation": 0}, {"text": "Kepada:", "confidence": 91.0, "left": 132, "top": 1633, "width": 95, "height": 26, "page": 0, "rotation": 0}, {"text": "Nomor", "confidence": 92.0, "left": 132, "top": 1666, "width": 78, "height": 20, "page": 0, "rotation": 0}, {"text": ":", "confidence": 92.0, "left": 335, "top": 1673, "width": 4, "height": 17, "page": 0, "rotation": 0}, {"text": "847748", "confidence": 95.0, "left": 354, "top": 1666, "width": 76, "height": 18, "page": 0, "rotation": 0}, {"text": "Bank", "confidence": 92.0, "left": 879, "top": 1667, "width": 58, "height": 20, "page": 0, "rotation": 0}, {"text": "/", "confidence": 92.0, "left": 945, "top": 1667, "width": 7, "height": 21, "page": 0, "rotation": 0}, {"text": "Pos", "confidence": 96.0, "left": 961, "top": 1667, "width": 43, "height": 21, "page": 0, "rotation": 0}, {"text": ":", "confidence": 88.0, "left": 1107, "top": 1672, "width": 4, "height": 13, "page": 0, "rotation": 0}, {"text": "BANK", "confidence": 92.0, "left": 1128, "top": 1667, "width": 63, "height": 18, "page": 0, "rotation": 0}, {"text": "NEGARA", "confidence": 91.0, "left": 1198, "top": 1667, "width": 98, "height": 18, "page": 0, "rotation": 0}, {"text": "INDONESIA", "confidence": 95.0, "left": 1304, "top": 1667, "width": 127, "height": 19, "page": 0, "rotation": 0}, {"text": "Nama", "confidence": 96.0, "left": 132, "top": 1701, "width": 68, "height": 20, "page": 0, "rotation": 0}, {"text": "Supplier", "confidence": 67.0, "left": 209, "top": 1701, "width": 96, "height": 25, "page": 0, "rotation": 0}, {"text": ";", "confidence": 65.0, "left": 335, "top": 1708, "width": 4, "height": 16, "page": 0, "rotation": 0}, {"text": "BADAN", "confidence": 91.0, "left": 354, "top": 1701, "width": 78, "height": 18, "page": 0, "rotation": 0}, {"text": "PUSAT", "confidence": 90.0, "left": 441, "top": 1701, "width": 77, "height": 18, "page": 0, "rotation": 0}, {"text": "STATISTIK", "confidence": 95.0, "left": 526, "top": 1701, "width": 117, "height": 18, "page": 0, "rotation": 0}, {"text": "PROP.", "confidence": 93.0, "left": 652, "top": 1701, "width": 70, "height": 18, "page": 0, "rotation": 0}, {"text": "SUMATERA", "confidence": 77.0, "left": 731, "top": 1701, "width": 129, "height": 19, "page": 0, "rotation": 0}, {"text": "Rekening", "confidence": 89.0, "left": 879, "top": 1702, "width": 109, "height": 25, "page": 0, "rotation": 0}, {"text": ":", "confidence": 89.0, "left": 1108, "top": 1707, "width": 3, "height": 13, "page": 0, "rotation": 0}, {"text": "989075019937", "confidence": 0.0, "left": 1127, "top": 1702, "width": 207, "height": 19, "page": 0, "rotation": 0}, {"text": "1000", "confidence": 0.0, "left": 1285, "top": 1697, "width": 52, "height": 34, "page": 0, "rotation": 0}, {"text": "BARAT", "confidence": 96.0, "left": 354, "top": 1724, "width": 77, "height": 31, "page": 0, "rotation": 0}, {"text": "a", "confidence": 55.0, "left": 1011, "top": 1737, "width": 15, "height": 4, "page": 0, "rotation": 0}, {"text": ".", "confidence": 94.0, "left": 1108, "top": 1742, "width": 3, "height": 3, "page": 0, "rotation": 0}, {"text": "NPWP2", "confidence": 90.0, "left": 132, "top": 1788, "width": 92, "height": 21, "page": 0, "rotation": 0}, {"text": ":", "confidence": 86.0, "left": 335, "top": 1796, "width": 4, "height": 16, "page": 0, "rotation": 0}, {"text": "0001858539201000", "confidence": 87.0, "left": 353, "top": 1788, "width": 208, "height": 19, "page": 0, "rotation": 0}, {"text": "ama", "confidence": 88.0, "left": 902, "top": 1777, "width": 49, "height": 15, "page": 0, "rotation": 0}, {"text": "sae", "confidence": 10.0, "left": 1108, "top": 1786, "width": 48, "height": 4, "page": 0, "rotation": 0}, {"text": ".", "confidence": 60.0, "left": 1419, "top": 1787, "width": 3, "height": 4, "page": 0, "rotation": 0}, {"text": "NOP", "confidence": 90.0, "left": 132, "top": 1824, "width": 55, "height": 21, "page": 0, "rotation": 0}, {"text": ":", "confidence": 86.0, "left": 335, "top": 1831, "width": 3, "height": 17, "page": 0, "rotation": 0}, {"text": "Uraian", "confidence": 89.0, "left": 132, "top": 1857, "width": 74, "height": 20, "page": 0, "rotation": 0}, {"text": ":", "confidence": 92.0, "left": 334, "top": 1861, "width": 3, "height": 14, "page": 0, "rotation": 0}, {"text": "PENGGANTIAN", "confidence": 91.0, "left": 354, "top": 1857, "width": 168, "height": 18, "page": 0, "rotation": 0}, {"text": "UANG", "confidence": 91.0, "left": 531, "top": 1857, "width": 66, "height": 18, "page": 0, "rotation": 0}, {"text": "PERSEDIAAN", "confidence": 91.0, "left": 605, "top": 1857, "width": 149, "height": 18, "page": 0, "rotation": 0}, {"text": "UNTUK", "confidence": 91.0, "left": 763, "top": 1857, "width": 79, "height": 19, "page": 0, "rotation": 0}, {"text": "KEPERLUAN", "confidence": 92.0, "left": 850, "top": 1857, "width": 140, "height": 19, "page": 0, "rotation": 0}, {"text": "BELANJA", "confidence": 91.0, "left": 999, "top": 1857, "width": 102, "height": 19, "page": 0, "rotation": 0}, {"text": "BARANG", "confidence": 92.0, "left": 1109, "top": 1858, "width": 98, "height": 18, "page": 0, "rotation": 0}, {"text": "DENGAN", "confidence": 92.0, "left": 1215, "top": 1858, "width": 97, "height": 18, "page": 0, "rotation": 0}, {"text": "NOMOR", "confidence": 91.0, "left": 1322, "top": 1858, "width": 88, "height": 18, "page": 0, "rotation": 0}, {"text": "SERTIFIKAT", "confidence": 91.0, "left": 1418, "top": 1858, "width": 134, "height": 18, "page": 0, "rotation": 0}, {"text": "BNT", "confidence": 91.0, "left": 1560, "top": 1858, "width": 46, "height": 18, "page": 0, "rotation": 0}, {"text": ":", "confidence": 91.0, "left": 1614, "top": 1863, "width": 3, "height": 13, "page": 0, "rotation": 0}, {"text": "BNT-", "confidence": 92.0, "left": 1627, "top": 1858, "width": 53, "height": 18, "page": 0, "rotation": 0}, {"text": "01424/191/691/2023", "confidence": 91.0, "left": 353, "top": 1884, "width": 214, "height": 18, "page": 0, "rotation": 0}, {"text": "TANGGAL", "confidence": 92.0, "left": 575, "top": 1884, "width": 111, "height": 19, "page": 0, "rotation": 0}, {"text": "3", "confidence": 96.0, "left": 694, "top": 1884, "width": 11, "height": 19, "page": 0, "rotation": 0}, {"text": "APRIL", "confidence": 94.0, "left": 712, "top": 1884, "width": 68, "height": 18, "page": 0, "rotation": 0}, {"text": "2023", "confidence": 94.0, "left": 787, "top": 1884, "width": 51, "height": 19, "page": 0, "rotation": 0}, {"text": "Semua", "confidence": 91.0, "left": 119, "top": 2060, "width": 81, "height": 21, "page": 0, "rotation": 0}, {"text": "bukti-bukti", "confidence": 88.0, "left": 210, "top": 2061, "width": 117, "height": 21, "page": 0, "rotation": 0}, {"text": "pengeluaran", "confidence": 88.0, "left": 337, "top": 2061, "width": 144, "height": 26, "page": 0, "rotation": 0}, {"text": "yang", "confidence": 93.0, "left": 490, "top": 2067, "width": 56, "height": 20, "page": 0, "rotation": 0}, {"text": "disahkan", "confidence": 91.0, "left": 555, "top": 2061, "width": 104, "height": 21, "page": 0, "rotation": 0}, {"text": "Pejabat", "confidence": 92.0, "left": 669, "top": 2061, "width": 88, "height": 26, "page": 0, "rotation": 0}, {"text": "Pembuat", "confidence": 92.0, "left": 766, "top": 2062, "width": 104, "height": 20, "page": 0, "rotation": 0}, {"text": "Komitmen", "confidence": 92.0, "left": 879, "top": 2062, "width": 115, "height": 21, "page": 0, "rotation": 0}, {"text": "telah", "confidence": 96.0, "left": 1003, "top": 2062, "width": 55, "height": 21, "page": 0, "rotation": 0}, {"text": "Padang,", "confidence": 95.0, "left": 1127, "top": 2059, "width": 95, "height": 26, "page": 0, "rotation": 0}, {"text": "28", "confidence": 96.0, "left": 1231, "top": 2060, "width": 29, "height": 20, "page": 0, "rotation": 0}, {"text": "April", "confidence": 96.0, "left": 1268, "top": 2059, "width": 51, "height": 26, "page": 0, "rotation": 0}, {"text": "2026", "confidence": 96.0, "left": 1328, "top": 2060, "width": 58, "height": 20, "page": 0, "rotation": 0}, {"text": "diuji", "confidence": 90.0, "left": 118, "top": 2091, "width": 46, "height": 26, "page": 0, "rotation": 0}, {"text": "dan", "confidence": 93.0, "left": 173, "top": 2091, "width": 42, "height": 21, "page": 0, "rotation": 0}, {"text": "dinyatakan", "confidence": 91.0, "left": 224, "top": 2091, "width": 125, "height": 26, "page": 0, "rotation": 0}, {"text": "memenuhi", "confidence": 92.0, "left": 359, "top": 2092, "width": 121, "height": 20, "page": 0, "rotation": 0}, {"text": "persyaratan", "confidence": 93.0, "left": 490, "top": 2093, "width": 136, "height": 25, "page": 0, "rotation": 0}, {"text": "untuk", "confidence": 93.0, "left": 636, "top": 2092, "width": 63, "height": 20, "page": 0, "rotation": 0}, {"text": "dilakukan", "confidence": 50.0, "left": 708, "top": 2092, "width": 109, "height": 20, "page": 0, "rotation": 0}, {"text": "pembayaran", "confidence": 92.0, "left": 827, "top": 2092, "width": 144, "height": 26, "page": 0, "rotation": 0}, {"text": "atas", "confidence": 92.0, "left": 980, "top": 2094, "width": 49, "height": 19, "page": 0, "rotation": 0}, {"text": "a.n", "confidence": 91.0, "left": 1127, "top": 2105, "width": 34, "height": 16, "page": 0, "rotation": 0}, {"text": "Kuasa", "confidence": 92.0, "left": 1171, "top": 2100, "width": 72, "height": 21, "page": 0, "rotation": 0}, {"text": "Pengguna", "confidence": 93.0, "left": 1253, "top": 2101, "width": 118, "height": 25, "page": 0, "rotation": 0}, {"text": "Anggaran", "confidence": 93.0, "left": 1379, "top": 2101, "width": 114, "height": 26, "page": 0, "rotation": 0}, {"text": "beban", "confidence": 91.0, "left": 119, "top": 2122, "width": 71, "height": 20, "page": 0, "rotation": 0}, {"text": "APBN,", "confidence": 92.0, "left": 198, "top": 2122, "width": 77, "height": 23, "page": 0, "rotation": 0}, {"text": "selanjutnya", "confidence": 93.0, "left": 285, "top": 2122, "width": 132, "height": 26, "page": 0, "rotation": 0}, {"text": "bukti-bukti", "confidence": 91.0, "left": 426, "top": 2122, "width": 118, "height": 21, "page": 0, "rotation": 0}, {"text": "pengeluaran", "confidence": 91.0, "left": 554, "top": 2122, "width": 144, "height": 26, "page": 0, "rotation": 0}, {"text": "dimaksud", "confidence": 92.0, "left": 708, "top": 2123, "width": 110, "height": 20, "page": 0, "rotation": 0}, {"text": "disimpan", "confidence": 92.0, "left": 828, "top": 2123, "width": 103, "height": 25, "page": 0, "rotation": 0}, {"text": "dan", "confidence": 96.0, "left": 940, "top": 2123, "width": 42, "height": 20, "page": 0, "rotation": 0}, {"text": "Pejabat", "confidence": 89.0, "left": 1127, "top": 2139, "width": 88, "height": 20, "page": 0, "rotation": 0}, {"text": "Penandatangan", "confidence": 92.0, "left": 1224, "top": 2139, "width": 183, "height": 20, "page": 0, "rotation": 0}, {"text": "SPM", "confidence": 96.0, "left": 1417, "top": 2139, "width": 54, "height": 20, "page": 0, "rotation": 0}, {"text": "ditatausahakan", "confidence": 91.0, "left": 118, "top": 2152, "width": 177, "height": 21, "page": 0, "rotation": 0}, {"text": "oleh", "confidence": 93.0, "left": 304, "top": 2153, "width": 48, "height": 20, "page": 0, "rotation": 0}, {"text": "Pejabat", "confidence": 92.0, "left": 362, "top": 2153, "width": 88, "height": 25, "page": 0, "rotation": 0}, {"text": "Penandatangan", "confidence": 90.0, "left": 459, "top": 2153, "width": 184, "height": 26, "page": 0, "rotation": 0}, {"text": "SPM", "confidence": 96.0, "left": 652, "top": 2153, "width": 55, "height": 21, "page": 0, "rotation": 0}, {"text": "!", "confidence": 59.0, "left": 1157, "top": 2144, "width": 6, "height": 20, "page": 0, "rotation": 0}, {"text": "9", "confidence": 93.0, "left": 1365, "top": 2144, "width": 13, "height": 20, "page": 0, "rotation": 0}, {"text": "Kebenaran", "confidence": 92.0, "left": 119, "top": 2182, "width": 126, "height": 19, "page": 0, "rotation": 0}, {"text": "perhitungan", "confidence": 92.0, "left": 255, "top": 2183, "width": 137, "height": 23, "page": 0, "rotation": 0}, {"text": "dan", "confidence": 95.0, "left": 401, "top": 2183, "width": 42, "height": 18, "page": 0, "rotation": 0}, {"text": "isi", "confidence": 95.0, "left": 453, "top": 2183, "width": 22, "height": 18, "page": 0, "rotation": 0}, {"text": "yang", "confidence": 93.0, "left": 484, "top": 2188, "width": 56, "height": 19, "page": 0, "rotation": 0}, {"text": "tertuang", "confidence": 82.0, "left": 549, "top": 2184, "width": 95, "height": 23, "page": 0, "rotation": 0}, {"text": "dalam", "confidence": 83.0, "left": 653, "top": 2184, "width": 70, "height": 18, "page": 0, "rotation": 0}, {"text": "SPM", "confidence": 95.0, "left": 733, "top": 2184, "width": 54, "height": 18, "page": 0, "rotation": 0}, {"text": "ini", "confidence": 95.0, "left": 797, "top": 2184, "width": 24, "height": 17, "page": 0, "rotation": 0}, {"text": "menjadi", "confidence": 93.0, "left": 831, "top": 2184, "width": 90, "height": 23, "page": 0, "rotation": 0}, {"text": "tanggung", "confidence": 92.0, "left": 929, "top": 2185, "width": 109, "height": 22, "page": 0, "rotation": 0}, {"text": "Hk", "confidence": 6.0, "left": 1139, "top": 2191, "width": 147, "height": 30, "page": 0, "rotation": 0}, {"text": "jawab", "confidence": 91.0, "left": 116, "top": 2210, "width": 70, "height": 26, "page": 0, "rotation": 0}, {"text": "Pejabat", "confidence": 91.0, "left": 195, "top": 2210, "width": 88, "height": 26, "page": 0, "rotation": 0}, {"text": "Penandatangan", "confidence": 91.0, "left": 292, "top": 2211, "width": 183, "height": 25, "page": 0, "rotation": 0}, {"text": "SPM.", "confidence": 91.0, "left": 485, "top": 2211, "width": 62, "height": 20, "page": 0, "rotation": 0}, {"text": "ES", "confidence": 36.0, "left": 1158, "top": 2207, "width": 88, "height": 35, "page": 0, "rotation": 0}, {"text": "-", "confidence": 73.0, "left": 1273, "top": 2234, "width": 8, "height": 8, "page": 0, "rotation": 0}, {"text": "Oke:", "confidence": 42.0, "left": 1139, "top": 2304, "width": 80, "height": 33, "page": 0, "rotation": 0}, {"text": "ie", "confidence": 24.0, "left": 1251, "top": 2301, "width": 30, "height": 22, "page": 0, "rotation": 0}, {"text": "Dokumen", "confidence": 92.0, "left": 119, "top": 2324, "width": 110, "height": 21, "page": 0, "rotation": 0}, {"text": "ini", "confidence": 96.0, "left": 239, "top": 2325, "width": 23, "height": 20, "page": 0, "rotation": 0}, {"text": "telah", "confidence": 93.0, "left": 271, "top": 2325, "width": 56, "height": 20, "page": 0, "rotation": 0}, {"text": "ditandatangani", "confidence": 91.0, "left": 336, "top": 2325, "width": 171, "height": 26, "page": 0, "rotation": 0}, {"text": "menggunakan", "confidence": 91.0, "left": 517, "top": 2325, "width": 165, "height": 26, "page": 0, "rotation": 0}, {"text": "sertifikat", "confidence": 90.0, "left": 691, "top": 2325, "width": 98, "height": 21, "page": 0, "rotation": 0}, {"text": "elektronik", "confidence": 91.0, "left": 797, "top": 2325, "width": 111, "height": 21, "page": 0, "rotation": 0}, {"text": "yang", "confidence": 96.0, "left": 916, "top": 2330, "width": 56, "height": 21, "page": 0, "rotation": 0}, {"text": "ca", "confidence": 27.0, "left": 1229, "top": 2328, "width": 4, "height": 4, "page": 0, "rotation": 0}, {"text": "Sa", "confidence": 25.0, "left": 1251, "top": 2324, "width": 26, "height": 8, "page": 0, "rotation": 0}, {"text": "diterbitkan", "confidence": 93.0, "left": 118, "top": 2356, "width": 119, "height": 21, "page": 0, "rotation": 0}, {"text": "oleh", "confidence": 96.0, "left": 247, "top": 2355, "width": 48, "height": 22, "page": 0, "rotation": 0}, {"text": "Balai", "confidence": 96.0, "left": 305, "top": 2355, "width": 56, "height": 22, "page": 0, "rotation": 0}, {"text": "Besar", "confidence": 93.0, "left": 371, "top": 2356, "width": 68, "height": 21, "page": 0, "rotation": 0}, {"text": "Sertifikat", "confidence": 91.0, "left": 446, "top": 2356, "width": 102, "height": 21, "page": 0, "rotation": 0}, {"text": "Elektronik", "confidence": 93.0, "left": 557, "top": 2356, "width": 114, "height": 21, "page": 0, "rotation": 0}, {"text": "(BSrE),", "confidence": 93.0, "left": 679, "top": 2356, "width": 84, "height": 26, "page": 0, "rotation": 0}, {"text": "BSSN.", "confidence": 91.0, "left": 773, "top": 2356, "width": 77, "height": 21, "page": 0, "rotation": 0}, {"text": "JEFRIO", "confidence": 91.0, "left": 1126, "top": 2357, "width": 92, "height": 21, "page": 0, "rotation": 0}, {"text": "MARTIYUS", "confidence": 91.0, "left": 1228, "top": 2357, "width": 134, "height": 21, "page": 0, "rotation": 0}, {"text": "poe", "confidence": 23.0, "left": 184, "top": 2395, "width": 35, "height": 15, "page": 0, "rotation": 0}, {"text": "Teh", "confidence": 14.0, "left": 267, "top": 2395, "width": 42, "height": 14, "page": 0, "rotation": 0}, {"text": "NIP", "confidence": 96.0, "left": 1127, "top": 2399, "width": 42, "height": 20, "page": 0, "rotation": 0}, {"text": "198807", "confidence": 30.0, "left": 1181, "top": 2399, "width": 80, "height": 20, "page": 0, "rotation": 0}, {"text": "162010121007", "confidence": 30.0, "left": 1268, "top": 2399, "width": 172, "height": 20, "page": 0, "rotation": 0}], "engine": "tesseract", "warnings": [], "rotation": 0, "tried_rotations": [0], "cache_hit": false}