{"text": "[Kode : BENO03] BADAN PUSAT STATISTIK BADAN PUSAT STATISTIK PROP. SUMATERA BARAT LAMPIRAN DAFTAR RINCIAN PERMINTAAN PEMBAYARAN Nomor : 00047/DRPP/019937/2026 Tanggal : 15 Juni 2026 Halaman: 1 dari 1 Detail COA Ro.Komp.Subkomp.item - Uraian 019937.010.524111.05401GG.2897QDB.A000000001.00000.2.0800.2.000000.000000 _ 003.052.0A.000355-Perjalanan dinas pembinaan statistik sektoral 500.000,00 SUMATERA BARAT, 15 Juni 2026 a.n. Kuasa Pengguna Anggaran 22°. Rejabareembuat Komitmen w ”—….—_- p —r He Be | S a FBS | Pr NIP 186804 166012111001 STSUMS N", "confidence": 77.77, "words": [{"text": "[Kode", "confidence": 93.0, "left": 1459, "top": 112, "width": 91, "height": 34, "page": 0, "rotation": 0}, {"text": ":", "confidence": 92.0, "left": 1563, "top": 120, "width": 7, "height": 19, "page": 0, "rotation": 0}, {"text": "BENO03]", "confidence": 62.0, "left": 1582, "top": 111, "width": 141, "height": 34, "page": 0, "rotation": 0}, {"text": "BADAN", "confidence": 91.0, "left": 692, "top": 174, "width": 117, "height": 27, "page": 0, "rotation": 0}, {"text": "PUSAT", "confidence": 92.0, "left": 823, "top": 173, "width": 115, "height": 27, "page": 0, "rotation": 0}, {"text": "STATISTIK", "confidence": 96.0, "left": 950, "top": 172, "width": 176, "height": 27, "page": 0, "rotation": 0}, {"text": "BADAN", "confidence": 92.0, "left": 467, "top": 235, "width": 117, "height": 27, "page": 0, "rotation": 0}, {"text": "PUSAT", "confidence": 92.0, "left": 598, "top": 234, "width": 115, "height": 27, "page": 0, "rotation": 0}, {"text": "STATISTIK", "confidence": 96.0, "left": 725, "top": 233, "width": 175, "height": 27, "page": 0, "rotation": 0}, {"text": "PROP.", "confidence": 93.0, "left": 913, "top": 232, "width": 105, "height": 26, "page": 0, "rotation": 0}, {"text": "SUMATERA", "confidence": 89.0, "left": 1032, "top": 231, "width": 193, "height": 26, "page": 0, "rotation": 0}, {"text": "BARAT", "confidence": 96.0, "left": 1237, "top": 230, "width": 115, "height": 26, "page": 0, "rotation": 0}, {"text": "LAMPIRAN", "confidence": 92.0, "left": 410, "top": 293, "width": 181, "height": 28, "page": 0, "rotation": 0}, {"text": "DAFTAR", "confidence": 93.0, "left": 606, "top": 292, "width": 141, "height": 27, "page": 0, "rotation": 0}, {"text": "RINCIAN", "confidence": 91.0, "left": 760, "top": 291, "width": 142, "height": 27, "page": 0, "rotation": 0}, {"text": "PERMINTAAN", "confidence": 91.0, "left": 916, "top": 289, "width": 230, "height": 28, "page": 0, "rotation": 0}, {"text": "PEMBAYARAN", "confidence": 90.0, "left": 1161, "top": 288, "width": 247, "height": 27, "page": 0, "rotation": 0}, {"text": "Nomor", "confidence": 89.0, "left": 99, "top": 378, "width": 86, "height": 50, "page": 0, "rotation": 0}, {"text": ":", "confidence": 89.0, "left": 392, "top": 399, "width": 4, "height": 16, "page": 0, "rotation": 0}, {"text": "00047/DRPP/019937/2026", "confidence": 28.0, "left": 407, "top": 391, "width": 348, "height": 25, "page": 0, "rotation": 0}, {"text": "Tanggal", "confidence": 93.0, "left": 97, "top": 435, "width": 104, "height": 44, "page": 0, "rotation": 0}, {"text": ":", "confidence": 93.0, "left": 392, "top": 448, "width": 4, "height": 17, "page": 0, "rotation": 0}, {"text": "15", "confidence": 91.0, "left": 409, "top": 442, "width": 28, "height": 23, "page": 0, "rotation": 0}, {"text": "Juni", "confidence": 92.0, "left": 447, "top": 442, "width": 52, "height": 23, "page": 0, "rotation": 0}, {"text": "2026", "confidence": 92.0, "left": 509, "top": 442, "width": 64, "height": 22, "page": 0, "rotation": 0}, {"text": "Halaman:", "confidence": 95.0, "left": 1399, "top": 476, "width": 129, "height": 22, "page": 0, "rotation": 0}, {"text": "1", "confidence": 90.0, "left": 1550, "top": 475, "width": 8, "height": 22, "page": 0, "rotation": 0}, {"text": "dari", "confidence": 95.0, "left": 1577, "top": 475, "width": 47, "height": 22, "page": 0, "rotation": 0}, {"text": "1", "confidence": 91.0, "left": 1645, "top": 475, "width": 9, "height": 21, "page": 0, "rotation": 0}, {"text": "Detail", "confidence": 95.0, "left": 254, "top": 553, "width": 77, "height": 23, "page": 0, "rotation": 0}, {"text": "COA", "confidence": 96.0, "left": 342, "top": 553, "width": 63, "height": 23, "page": 0, "rotation": 0}, {"text": "Ro.Komp.Subkomp.item", "confidence": 82.0, "left": 255, "top": 632, "width": 316, "height": 28, "page": 0, "rotation": 0}, {"text": "-", "confidence": 92.0, "left": 581, "top": 643, "width": 9, "height": 4, "page": 0, "rotation": 0}, {"text": "Uraian", "confidence": 92.0, "left": 600, "top": 631, "width": 83, "height": 22, "page": 0, "rotation": 0}, {"text": "019937.010.524111.05401GG.2897QDB.A000000001.00000.2.0800.2.000000.000000", "confidence": 59.0, "left": 107, "top": 679, "width": 1132, "height": 29, "page": 0, "rotation": 0}, {"text": "_", "confidence": 96.0, "left": 1419, "top": 674, "width": 304, "height": 65, "page": 0, "rotation": 0}, {"text": "003.052.0A.000355-Perjalanan", "confidence": 91.0, "left": 254, "top": 764, "width": 404, "height": 28, "page": 0, "rotation": 0}, {"text": "dinas", "confidence": 93.0, "left": 669, "top": 764, "width": 68, "height": 21, "page": 0, "rotation": 0}, {"text": "pembinaan", "confidence": 91.0, "left": 747, "top": 763, "width": 142, "height": 28, "page": 0, "rotation": 0}, {"text": "statistik", "confidence": 88.0, "left": 900, "top": 762, "width": 96, "height": 22, "page": 0, "rotation": 0}, {"text": "sektoral", "confidence": 88.0, "left": 1005, "top": 761, "width": 101, "height": 23, "page": 0, "rotation": 0}, {"text": "500.000,00", "confidence": 87.0, "left": 1571, "top": 759, "width": 144, "height": 25, "page": 0, "rotation": 0}, {"text": "SUMATERA", "confidence": 92.0, "left": 1142, "top": 1041, "width": 161, "height": 23, "page": 0, "rotation": 0}, {"text": "BARAT,", "confidence": 96.0, "left": 1313, "top": 1041, "width": 102, "height": 25, "page": 0, "rotation": 0}, {"text": "15", "confidence": 96.0, "left": 1429, "top": 1040, "width": 28, "height": 22, "page": 0, "rotation": 0}, {"text": "Juni", "confidence": 90.0, "left": 1467, "top": 1040, "width": 52, "height": 22, "page": 0, "rotation": 0}, {"text": "2026", "confidence": 90.0, "left": 1529, "top": 1040, "width": 63, "height": 22, "page": 0, "rotation": 0}, {"text": "a.n.", "confidence": 89.0, "left": 1142, "top": 1083, "width": 48, "height": 44, "page": 0, "rotation": 0}, {"text": "Kuasa", "confidence": 92.0, "left": 1200, "top": 1086, "width": 80, "height": 22, "page": 0, "rotation": 0}, {"text": "Pengguna", "confidence": 93.0, "left": 1291, "top": 1085, "width": 131, "height": 28, "page": 0, "rotation": 0}, {"text": "Anggaran", "confidence": 92.0, "left": 1431, "top": 1085, "width": 125, "height": 28, "page": 0, "rotation": 0}, {"text": "22°.", "confidence": 0.0, "left": 1052, "top": 1124, "width": 83, "height": 39, "page": 0, "rotation": 0}, {"text": "Rejabareembuat", "confidence": 0.0, "left": 1145, "top": 1133, "width": 221, "height": 23, "page": 0, "rotation": 0}, {"text": "Komitmen", "confidence": 93.0, "left": 1376, "top": 1133, "width": 129, "height": 22, "page": 0, "rotation": 0}, {"text": "w", "confidence": 64.0, "left": 1024, "top": 1210, "width": 22, "height": 19, "page": 0, "rotation": 0}, {"text": "”—….—_-", "confidence": 44.0, "left": 1065, "top": 1192, "width": 241, "height": 47, "page": 0, "rotation": 0}, {"text": "p", "confidence": 43.0, "left": 1466, "top": 1224, "width": 2, "height": 2, "page": 0, "rotation": 0}, {"text": "—r", "confidence": 26.0, "left": 970, "top": 1279, "width": 20, "height": 8, "page": 0, "rotation": 0}, {"text": "He", "confidence": 57.0, "left": 1117, "top": 1279, "width": 21, "height": 14, "page": 0, "rotation": 0}, {"text": "Be", "confidence": 35.0, "left": 1184, "top": 1278, "width": 24, "height": 16, "page": 0, "rotation": 0}, {"text": "|", "confidence": 79.0, "left": 0, "top": 1363, "width": 1, "height": 11, "page": 0, "rotation": 0}, {"text": "S", "confidence": 63.0, "left": 1009, "top": 1329, "width": 31, "height": 43, "page": 0, "rotation": 0}, {"text": "a", "confidence": 46.0, "left": 1102, "top": 1266, "width": 129, "height": 108, "page": 0, "rotation": 0}, {"text": "FBS", "confidence": 19.0, "left": 1255, "top": 1335, "width": 86, "height": 33, "page": 0, "rotation": 0}, {"text": "|", "confidence": 92.0, "left": 0, "top": 1377, "width": 1, "height": 19, "page": 0, "rotation": 0}, {"text": "Pr", "confidence": 49.0, "left": 1030, "top": 1365, "width": 63, "height": 58, "page": 0, "rotation": 0}, {"text": "NIP", "confidence": 52.0, "left": 1144, "top": 1380, "width": 46, "height": 22, "page": 0, "rotation": 0}, {"text": "186804", "confidence": 37.0, "left": 1219, "top": 1381, "width": 57, "height": 17, "page": 0, "rotation": 0}, {"text": "166012111001", "confidence": 62.0, "left": 1300, "top": 1378, "width": 188, "height": 23, "page": 0, "rotation": 0}, {"text": "STSUMS", "confidence": 54.0, "left": 1086, "top": 1409, "width": 120, "height": 33, "page": 0, "rotation": 0}, {"text": "N", "confidence": 48.0, "left": 1306, "top": 1468, "width": 9, "height": 16, "page": 0, "rotation": 0}], "engine": "tesseract", "warnings": [], "rotation": 0, "tried_rotations": [0], "cache_hit": false}